{
  "external_api": {
    "backend": {
      "url": "https://qabkket.kuepa.edu.co"
    },
    "main_socket": {
      "url": "https://qabkket.kuepa.edu.co"
    },
    "lms" : {
      "url" : "https://qalms.kuepa.edu.co/"
    }
  },
  "main_external_api": "backend",
  "main_external_socket": "main_socket",
  "has_site": true,
  "default_language": "es",
  "secure_home": "/app",
  "host": "lms.kuepa.test",
  "available_hosts": {
    "kuepa-colombia.lms.kuepa.test": {
      "alliance_slug": "kuepa-colombia"
    },
    "iq.edu.test": {
      "alliance_slug": "iq-primaria"
    },
    "plan-de-vacunacion-rd.lms.kuepa.test": {
      "alliance_slug": "plan-de-vacunacion-rd"
    },
    "leading.test": {
      "alliance_slug": "leading-education"
    },
    "capp.test": {
      "alliance_slug": "capp"
    }
  },
  "google_analytics": "UA-12312312-1",
  "customs": {
    "sis": "https://qasis.kuepa.edu.co/",
    "crm": "https://qacrm.kuepa.edu.co/"
  }
}